unimacro/BrowseGrammar.py
unimacro/BrowseGrammarApp.py
unimacro/D_.py
unimacro/D_train.py
unimacro/DialogServer.py
unimacro/TrainDialog.py
unimacro/__init__.py
unimacro/__init__.py.orig
unimacro/_control.py
unimacro/check_unimacro_grammars.py
unimacro/dos83.py
unimacro/foldersrememberdialog.py
unimacro/iban.py
unimacro/listdialogs.py
unimacro/lynote.py
unimacro/namelist.py
unimacro/natlinkutilsbj.py
unimacro/nld_spokenforms.ini
unimacro/scintillacon.py
unimacro/spokenforms.py
unimacro/testDialogForDictationGrammar.py
unimacro/unimacro_tracing.py
unimacro/unimacrofoldersremembertemplate.py
unimacro/windowinfo.py
unimacro/windowparameters.py
unimacro/xxxxxxxpythonwin_dict.py
unimacro/xxxxxxxunimacro_wxpythondialogs.py
unimacro/OtherUnimacroGrammars/_calculator.py
unimacro/OtherUnimacroGrammars/_keystrokes.py
unimacro/OtherUnimacroGrammars/_latex.py
unimacro/OtherUnimacroGrammars/_number extended.py
unimacro/OtherUnimacroGrammars/_oops.py
unimacro/OtherUnimacroGrammars/_repeat.py
unimacro/OtherUnimacroGrammars/_testtrayicon.py
unimacro/OtherUnimacroGrammars/_unimacrotest.py
unimacro/OtherUnimacroGrammars/excel.py
unimacro/OtherUnimacroGrammars/frescobaldi.py
unimacro/OtherUnimacroGrammars/solitaire.py
unimacro/OtherUnimacroGrammars/winword_variable.py
unimacro/OtherUnimacroGrammars/xxxxnatspeak_dialog.py
unimacro/UnimacroGrammars/README.txt
unimacro/UnimacroGrammars/__init__.py
unimacro/UnimacroGrammars/_brackets.py
unimacro/UnimacroGrammars/_clickbyvoice.py
unimacro/UnimacroGrammars/_debug_natlink.py.txt
unimacro/UnimacroGrammars/_debug_unimacro.py.txt
unimacro/UnimacroGrammars/_folders fillinstancevariables.txt
unimacro/UnimacroGrammars/_folders.py
unimacro/UnimacroGrammars/_general.py
unimacro/UnimacroGrammars/_lines.py
unimacro/UnimacroGrammars/_number simple.py
unimacro/UnimacroGrammars/_tags.py
unimacro/UnimacroGrammars/_tasks.py
unimacro/UnimacroGrammars/rememberdialog.py
unimacro/UnimacroGrammars/settings folders grammar.txt
unimacro/defaulticons/idi_down.ico
unimacro-4.1.6.dist-info/entry_points.txt
unimacro-4.1.6.dist-info/WHEEL
unimacro-4.1.6.dist-info/METADATA
unimacro-4.1.6.dist-info/RECORD
