Metadata-Version: 2.1
Name: unimacro
Version: 4.1.6
Summary: Unimacro __init__
Author-email: "Quintijn Hoogenboom (maintainer)" <q.hoogenboom@antenna.nl>
Requires-Python: >=3.10
Classifier: Development Status :: 4 - Beta
Classifier: Topic :: Multimedia :: Sound/Audio :: Speech
Classifier: Topic :: Scientific/Engineering :: Human Machine Interfaces
Classifier: Environment :: Win32 (MS Windows)
Classifier: Intended Audience :: Developers
Classifier: Operating System :: Microsoft :: Windows
Classifier: Programming Language :: Python :: 3.9
Classifier: Programming Language :: Python :: 3.10
Classifier: Programming Language :: Python :: 3.11
Classifier: Programming Language :: Python :: Implementation :: CPython
Classifier: Topic :: Multimedia :: Sound/Audio :: Speech
Classifier: Topic :: Software Development :: Libraries :: Python Modules
Requires-Dist: dtactions >= 1.6.2
Requires-Dist: debugpy >= 1.2.0
Requires-Dist: pywin32 >= 304
Requires-Dist: natlinkcore >= 5.4.1
Requires-Dist: FreeSimpleGUI>=5.1.0
Requires-Dist: pyenvutils ; extra == "dev"
Requires-Dist: entry-point-inspector ; extra == "dev"
Requires-Dist: build ; extra == "dev"
Requires-Dist: pytest >=7.1.2 ; extra == "test"
Requires-Dist: flake8 ; extra == "test"
Project-URL: homepage, https://qh.antenna.nl/unimacro/
Project-URL: repository, https://github.com/dictation-toolbox/unimacro
Project-URL: source, https://github.com/dictation-toolbox/unimacro
Provides-Extra: dev
Provides-Extra: test
